README.md
setup.py
kitkit.egg-info/PKG-INFO
kitkit.egg-info/SOURCES.txt
kitkit.egg-info/dependency_links.txt
kitkit.egg-info/top_level.txt
wu/__init__.py
wu/wy.py